[
    {
      "value": "Moins de 100 Millons GNF",
      "label": "Moins de 100 Millons GNF"
      
    },
    {
        "value": "Entre 100 de 200 Millons GNF",
        "label": "Entre 100 de 200 Millons GNF"
    },
    {
        "value": "Entre 200 de 1 Millard GNF",
        "label": "Entre 200 de 1 Millard GNF"
    },
    {
        "value": "Entre 1 de 20 Millards GNF",
        "label": "Entre 1 de 20 Millards GNF"
    },
    {
        "value": ">20 Millards GNF",
        "label":">20 Millards GNF"
    }
 
  ]